setup.py
malconstrict/__init__.py
malconstrict/exceptions.py
malconstrict/helpers.py
malconstrict/malapi.py
malconstrict/models.py
malconstrict.egg-info/PKG-INFO
malconstrict.egg-info/SOURCES.txt
malconstrict.egg-info/dependency_links.txt
malconstrict.egg-info/not-zip-safe
malconstrict.egg-info/requires.txt
malconstrict.egg-info/top_level.txt