Metadata-Version: 1.0
Name: malconstrict
Version: 0.1
Summary: Python wrapper to the Unofficial MyAnimeList API
Home-page: http://github.com/ear7631/malconstrict
Author: Eitan Romanoff
Author-email: ear7631@gmail.com
License: BSD
Keywords: myanimelist anime
Platform: UNKNOWN
Classifier: Development Status :: 3 - Alpha
Classifier: Intended Audience :: Developers
Classifier: License :: OSI Approved :: BSD License
Classifier: Programming Language :: Python :: 2
